alex_tech_logging_library/__init__.py
alex_tech_logging_library/__init__2.py
alex_tech_logging_library-0.1.6.dist-info/METADATA
alex_tech_logging_library-0.1.6.dist-info/WHEEL
alex_tech_logging_library-0.1.6.dist-info/top_level.txt
alex_tech_logging_library-0.1.6.dist-info/RECORD
