Metadata-Version: 2.1
Name: alex_tech_logging_library
Version: 0.1.6
Summary: A custom logging library built on Python's standard logging module. It provides a simple way to set up a logger with file and console handlers.
Home-page: 
Author: Tapan Bhatnagar
Author-email: tapan@alexandriatechnology.com
Classifier: Programming Language :: Python :: 3
Classifier: License :: OSI Approved :: MIT License
Classifier: Operating System :: OS Independent
